cillow/__init__.py
cillow/client.py
cillow/code_meta.py
cillow/importhook.py
cillow/interpreter.py
cillow/logger.py
cillow/modutils.py
cillow/shell.py
cillow/switchable.py
cillow/types.py
cillow/patch/__init__.py
cillow/patch/prebuilt.py
cillow/server/__init__.py
cillow/server/_process.py
cillow/server/client_manager.py
cillow/server/request_worker.py
cillow-1.0.0.dist-info/LICENSE
cillow-1.0.0.dist-info/METADATA
cillow-1.0.0.dist-info/WHEEL
cillow-1.0.0.dist-info/top_level.txt
cillow-1.0.0.dist-info/RECORD
