Metadata-Version: 2.2
Name: cillow
Version: 1.0.0
Summary: Code Interpreter Library
Author-email: Harsh Verma <synacktra.work@gmail.com>
Project-URL: Documentation, https://synacktra.is-a-dev/cillow/
Project-URL: Homepage, https://synacktra.is-a-dev/cillow/
Project-URL: Repository, https://github.com/synacktraa/cillow
Keywords: python
Classifier: Intended Audience :: Developers
Classifier: Programming Language :: Python
Classifier: Programming Language :: Python :: 3
Classifier: Programming Language :: Python :: 3.10
Classifier: Programming Language :: Python :: 3.11
Classifier: Programming Language :: Python :: 3.12
Classifier: Programming Language :: Python :: 3.13
Classifier: Topic :: Software Development :: Libraries :: Python Modules
Requires-Python: <4.0,>=3.10
License-File: LICENSE
Requires-Dist: loguru>=0.7.0
Requires-Dist: matplotlib>=3.8.0
Requires-Dist: pillow>=10.0.0
Requires-Dist: pyzmq>=25.0.0
